plom/__init__.py
plom/core.py
plom/manifold.py
plom/plotting.py
plom/preprocessing.py
plom/sampling.py
plom/utils.py
plom/lib/potential_eigen.dll
plom/lib/potential_eigen.so
plom/lib/potential_native.dll
plom/lib/potential_native.so
plom/test_scripts/check_potential_eigen.py
plom/test_scripts/check_potential_native.py
pyplom-2.0.1.dist-info/LICENSE
pyplom-2.0.1.dist-info/METADATA
pyplom-2.0.1.dist-info/WHEEL
pyplom-2.0.1.dist-info/top_level.txt
pyplom-2.0.1.dist-info/RECORD
