Metadata-Version: 2.1
Name: pyplom
Version: 2.0.1
Summary: Probabilistic Learning on Manifolds (PLoM)
Author-email: Philippe Hawi <hawi@usc.edu>
License: MIT License
Project-URL: Repository, https://github.com/philippe-hawi/PLoM
Requires-Python: >=3.8
License-File: LICENSE
Requires-Dist: numpy>=1.20
Requires-Dist: scipy>=1.7
Requires-Dist: joblib>=1.1
Requires-Dist: matplotlib
